headless_klaviyo-0.2.1.dist-info/licenses/LICENSE
kcli/__init__.py
kcli/constants.py
kcli/helpers.py
kcli/kcli.py
headless_klaviyo-0.2.1.dist-info/METADATA
headless_klaviyo-0.2.1.dist-info/WHEEL
headless_klaviyo-0.2.1.dist-info/entry_points.txt
headless_klaviyo-0.2.1.dist-info/top_level.txt
headless_klaviyo-0.2.1.dist-info/RECORD
