Metadata-Version: 2.4
Name: headless-klaviyo
Version: 0.2.1
Summary: Command line interface for interacting with Klaviyo resources
Author-email: Klaviyo Developer Experience Team <developers@klaviyo.com>
Requires-Python: >=3.10
License-File: LICENSE
Requires-Dist: klaviyo-api<19.0.0,>=18.0.0
Requires-Dist: rich<14.0.0,>=13.9.4
Requires-Dist: rich-click<2.0.0,>=1.8.6
Requires-Dist: survey<6.0.0,>=5.4.2
Dynamic: license-file
